{
  "publicPath": "/dist/",
  "all": [
    "2.8584521b2609a5985e85.js",
    "profile.jpeg?aaa8d62f6ab4ba0f7e74ad613b4624b1",
    "alipay.png?c02309bcf4fe8c30af428f1dba578d76",
    "weixin.png?8c285cca0449d546aab091d0a2a2d30c",
    "0.5380f45b99547586f12b.js",
    "1.1e506a02271400d5343e.js",
    "fonts/element-icons.6f0a763.ttf",
    "3.e513a66ace9c97922547.js",
    "vendor.eeb92db4fe1a30cb68de.js",
    "app.26a431afad74c96eed82.js",
    "manifest.136a8856ab03e4b624eb.js",
    "common.26a431afad74c96eed82.css"
  ],
  "initial": [
    "manifest.136a8856ab03e4b624eb.js",
    "vendor.eeb92db4fe1a30cb68de.js",
    "app.26a431afad74c96eed82.js",
    "common.26a431afad74c96eed82.css"
  ],
  "async": [
    "2.8584521b2609a5985e85.js",
    "0.5380f45b99547586f12b.js",
    "1.1e506a02271400d5343e.js",
    "3.e513a66ace9c97922547.js"
  ],
  "modules": {
    "10471236": [
      9,
      11,
      1
    ],
    "36098898": [
      8,
      6
    ],
    "38004920": [
      9,
      11,
      1
    ],
    "78641695": [
      8,
      6
    ],
    "88401450": [
      8,
      6
    ],
    "d487f6ca": [
      8,
      6
    ],
    "663fd078": [
      8,
      6
    ],
    "22a1bf28": [
      8,
      6
    ],
    "5f28dc84": [
      8,
      6
    ],
    "1676ee48": [
      8,
      6
    ],
    "5e0ac330": [
      8,
      6
    ],
    "6ad4138d": [
      8,
      6
    ],
    "75a56a68": [
      8,
      6
    ],
    "ab5fe37a": [
      8,
      6
    ],
    "8dd4c728": [
      8,
      6
    ],
    "62247bda": [
      8,
      6
    ],
    "13f3b9c5": [
      8,
      6
    ],
    "c8abd9b6": [
      8,
      6
    ],
    "087c22cd": [
      8,
      6
    ],
    "1559eac4": [
      8,
      6
    ],
    "d77a5a1e": [
      8,
      6
    ],
    "0dcb5dad": [
      8,
      6
    ],
    "3fa20de8": [
      8,
      6
    ],
    "06ceb31c": [
      8,
      6
    ],
    "186d57c2": [
      8,
      6
    ],
    "00b347ed": [
      8,
      6
    ],
    "e2cfd34a": [
      8,
      6
    ],
    "0101ec20": [
      8,
      6
    ],
    "6b2ea003": [
      8,
      6
    ],
    "471e4104": [
      8,
      6
    ],
    "69c7b8a5": [
      8,
      6
    ],
    "1f150d57": [
      8,
      6
    ],
    "0d578d42": [
      8,
      6
    ],
    "03ddff89": [
      8,
      6
    ],
    "d7b6d732": [
      8,
      6
    ],
    "48d95adb": [
      8,
      6
    ],
    "74a6d604": [
      8,
      6
    ],
    "207c6500": [
      8,
      6
    ],
    "022f9212": [
      8,
      6
    ],
    "8cfa0420": [
      8,
      6
    ],
    "577b9fc2": [
      8,
      6
    ],
    "4062100e": [
      8,
      6
    ],
    "e6f9f6e0": [
      8,
      6
    ],
    "41447cc7": [
      8,
      6
    ],
    "0974ea26": [
      8,
      6
    ],
    "6bb4aff6": [
      8,
      6
    ],
    "4ed442af": [
      8,
      6
    ],
    "3e8d14fe": [
      8,
      6
    ],
    "00f05a46": [
      8,
      6
    ],
    "296c5890": [
      8,
      6
    ],
    "05b058ff": [
      8,
      6
    ],
    "3fe97d03": [
      8,
      6
    ],
    "b27f2364": [
      8,
      6
    ],
    "32eb5f54": [
      8,
      6
    ],
    "7a4dd304": [
      8,
      6
    ],
    "730d215c": [
      9,
      11,
      1
    ],
    "c8d42dec": [
      8,
      6
    ],
    "23703c4a": [
      9,
      11,
      1
    ],
    "0528dfbb": [
      9,
      11,
      1
    ],
    "da4a8658": [
      9,
      11,
      1
    ],
    "2e430e1b": [
      9,
      11,
      1
    ],
    "0307e73b": [
      9,
      11,
      1
    ],
    "8673e78e": [
      9,
      11,
      1
    ],
    "5143fdf2": [
      9,
      11,
      1
    ],
    "048af4b6": [
      9,
      11,
      1
    ],
    "80617efa": [
      9,
      11,
      1
    ],
    "5be7faa4": [
      8,
      6
    ],
    "ade24bbe": [
      8,
      6
    ],
    "38202b97": [
      8,
      6
    ],
    "66e59e70": [
      8,
      6
    ],
    "a6be5c4e": [
      8,
      6
    ],
    "7e2b481d": [
      8,
      6
    ],
    "09565642": [
      8,
      6
    ],
    "488dbc82": [
      8,
      6
    ],
    "210753a2": [
      8,
      6
    ],
    "273b0abc": [
      8,
      6
    ],
    "c68d3994": [
      8,
      6
    ],
    "784b1e10": [
      8,
      6
    ],
    "1c1ea810": [
      8,
      6
    ],
    "7ff94e1e": [
      8,
      6
    ],
    "fc2452bc": [
      8,
      6
    ],
    "7b696ca6": [
      8,
      6
    ],
    "c230d3a6": [
      8,
      6
    ],
    "4bd34c72": [
      8,
      6
    ],
    "cc0f83fc": [
      8,
      6
    ],
    "128cfe46": [
      8,
      6
    ],
    "7088e67c": [
      8,
      6
    ],
    "6e3ffab4": [
      8,
      6
    ],
    "6bbf99df": [
      8,
      6
    ],
    "14754af9": [
      8,
      6
    ],
    "0d8f4b9a": [
      8,
      6
    ],
    "721340a3": [
      8,
      6
    ],
    "6eb0740f": [
      8,
      6
    ],
    "0f40bd54": [
      8,
      6
    ],
    "4d282c2c": [
      8,
      6
    ],
    "509b3a94": [
      8,
      6
    ],
    "7f63602e": [
      8,
      6
    ],
    "4bb2791b": [
      8,
      6
    ],
    "aca3df86": [
      8,
      6
    ],
    "b283af1a": [
      8,
      6
    ],
    "370e416e": [
      9,
      11,
      1
    ],
    "6c103e4a": [
      8,
      6
    ],
    "5ee28d5e": [
      8,
      6
    ],
    "3165a5ba": [
      9,
      11,
      1
    ],
    "3621b072": [
      8,
      6
    ],
    "4787e8fa": [
      8,
      6
    ],
    "7f8e0398": [
      8,
      6
    ],
    "546e7b14": [
      8,
      6
    ],
    "b1884168": [
      9,
      11,
      1
    ],
    "2ec3b6d5": [
      9,
      11,
      1
    ],
    "521d97aa": [
      9,
      11,
      1
    ],
    "5a452fe8": [
      9,
      11,
      1
    ],
    "36a13df6": [
      9,
      11,
      1
    ],
    "1a25f191": [
      9,
      11,
      1
    ],
    "f6ea4de2": [
      9,
      11,
      1
    ],
    "63a472dd": [
      9,
      11,
      1
    ],
    "41021c62": [
      9,
      11,
      1
    ],
    "3c70e24e": [
      9,
      11,
      1
    ],
    "48ecb3a6": [
      8,
      6
    ],
    "7c94dcee": [
      8,
      6
    ],
    "66c3b8d7": [
      8,
      6
    ],
    "4dc451be": [
      8,
      6
    ],
    "dd173948": [
      8,
      6
    ],
    "2776a989": [
      8,
      6
    ],
    "d4634008": [
      8,
      6
    ],
    "afdade94": [
      8,
      6
    ],
    "20664c64": [
      8,
      6
    ],
    "2e286028": [
      8,
      6
    ],
    "0adf034e": [
      8,
      6
    ],
    "162cdba2": [
      8,
      6
    ],
    "242df25f": [
      8,
      6
    ],
    "4e95acfe": [
      8,
      6
    ],
    "5ccca8b4": [
      8,
      6
    ],
    "26e8cdb1": [
      8,
      6
    ],
    "73812d52": [
      8,
      6
    ],
    "9578d1e8": [
      8,
      6
    ],
    "632ab6d4": [
      8,
      6
    ],
    "3a5f3eb8": [
      8,
      6
    ],
    "5c912fee": [
      8,
      6
    ],
    "4e2faacf": [
      8,
      6
    ],
    "7f446cbe": [
      8,
      6
    ],
    "eae9ee38": [
      8,
      6
    ],
    "b560dbf6": [
      8,
      6
    ],
    "f9ffb194": [
      8,
      6
    ],
    "154fd5af": [
      8,
      6
    ],
    "7141e74a": [
      8,
      6
    ],
    "8f76f6ba": [
      8,
      6
    ],
    "3ee9b7a6": [
      8,
      6
    ],
    "7a18dc9a": [
      8,
      6
    ],
    "a9a844da": [
      8,
      6
    ],
    "278fda80": [
      8,
      6
    ],
    "e464faac": [
      8,
      6
    ],
    "5b3b6a79": [
      8,
      6
    ],
    "15548e9f": [
      8,
      6
    ],
    "21f279cc": [
      8,
      6
    ],
    "160aaf9a": [
      8,
      6
    ],
    "5babb94c": [
      8,
      6
    ],
    "3823f8ba": [
      8,
      6
    ],
    "8548ddaa": [
      8,
      6
    ],
    "2fc5460e": [
      8,
      6
    ],
    "51806b9c": [
      8,
      6
    ],
    "2c18c88e": [
      8,
      6
    ],
    "5ea555ab": [
      8,
      6
    ],
    "e2f3e3a0": [
      8,
      6
    ],
    "3c47d9fd": [
      8,
      6
    ],
    "730fe618": [
      8,
      6
    ],
    "5c3d6d53": [
      8,
      6
    ],
    "c8dd1d1e": [
      8,
      6
    ],
    "77690d08": [
      8,
      6
    ],
    "97c67ba2": [
      8,
      6
    ],
    "2bfe557c": [
      8,
      6
    ],
    "0e4570ba": [
      8,
      6
    ],
    "596d0e18": [
      8,
      6
    ],
    "13442edc": [
      8,
      6
    ],
    "1be614b1": [
      8,
      6
    ],
    "39086c95": [
      8,
      6
    ],
    "2c62035c": [
      8,
      6
    ],
    "4f40fee5": [
      8,
      6
    ],
    "7c278af4": [
      8,
      6
    ],
    "00f8ad32": [
      8,
      6
    ],
    "1f2965d6": [
      8,
      6
    ],
    "5abc1ef8": [
      8,
      6
    ],
    "32b2dbc7": [
      8,
      6
    ],
    "49a8574a": [
      8,
      6
    ],
    "8fc41768": [
      8,
      6
    ],
    "0d8698ec": [
      8,
      6
    ],
    "58f7192d": [
      8,
      6
    ],
    "637ef742": [
      8,
      6
    ],
    "5234db72": [
      8,
      6
    ],
    "6dd7fcae": [
      8,
      6
    ],
    "96025eb0": [
      8,
      6
    ],
    "510ec49e": [
      8,
      6
    ],
    "51259a42": [
      8,
      6
    ],
    "256c6829": [
      8,
      6
    ],
    "5670a8da": [
      8,
      6
    ],
    "d3700b98": [
      8,
      6
    ],
    "1fb8798f": [
      8,
      6
    ],
    "8d2f3836": [
      8,
      6
    ],
    "8996c142": [
      8,
      6
    ],
    "ac025b7c": [
      8,
      6
    ],
    "44fdb3e2": [
      8,
      6
    ],
    "a1521dda": [
      8,
      6
    ],
    "7a13c31d": [
      8,
      6
    ],
    "212eaeb6": [
      8,
      6
    ],
    "720c7cd8": [
      8,
      6
    ],
    "7d40c4a4": [
      8,
      6
    ],
    "a1e3016c": [
      8,
      6
    ],
    "8c33f342": [
      8,
      6
    ],
    "22e599d2": [
      8,
      6
    ],
    "d64d959c": [
      8,
      6
    ],
    "3028b508": [
      8,
      6
    ],
    "39fdec0a": [
      8,
      6
    ],
    "167f2622": [
      8,
      6
    ],
    "55ef1732": [
      8,
      6
    ],
    "484b12de": [
      8,
      6
    ],
    "14cc2b1f": [
      8,
      6
    ],
    "b28cc686": [
      8,
      6
    ],
    "4d7e3194": [
      8,
      6
    ],
    "3821e312": [
      8,
      6
    ],
    "01f94952": [
      8,
      6
    ],
    "37a5e7e6": [
      9,
      11,
      1
    ],
    "473654c5": [
      9,
      11,
      1
    ],
    "9128c234": [
      8,
      6
    ],
    "89f1919a": [
      9,
      11,
      1
    ],
    "3cb78b8f": [
      5
    ],
    "b56a98a6": [
      4,
      2,
      3
    ],
    "415783f7": [
      4,
      2,
      3
    ],
    "2d5b63be": [
      4,
      2,
      3
    ],
    "4e6975ac": [
      0
    ],
    "43b29841": [
      7
    ],
    "36af08e5": [
      5
    ],
    "8f8a68be": [
      5
    ],
    "d9b4a9fe": [
      4,
      2,
      3
    ],
    "72f1388e": [
      4,
      2,
      3
    ],
    "c4e923f2": [
      4,
      2,
      3
    ],
    "5e25b282": [
      4,
      2,
      3
    ],
    "2487d8c1": [
      4,
      2,
      3
    ],
    "004e9016": [
      4,
      2,
      3
    ],
    "e0e2c36e": [
      4,
      2,
      3
    ],
    "343cea61": [
      4,
      2,
      3
    ],
    "2dd55663": [
      4,
      2,
      3
    ],
    "35fbbaaf": [
      4,
      2,
      3
    ],
    "5e166dea": [
      4,
      2,
      3
    ],
    "380f3ccf": [
      4,
      2,
      3
    ],
    "59206b96": [
      0
    ],
    "02935d5a": [
      0
    ],
    "66bbfeaa": [
      7
    ],
    "5222d922": [
      7
    ],
    "a94eb472": [
      5
    ],
    "01e3176a": [
      4,
      2,
      3
    ],
    "1d42f8d6": [
      0
    ],
    "260b802b": [
      7
    ]
  }
}